scatterminal/__init__.py
scatterminal/canvas_layer_model.py
scatterminal/common.py
scatterminal/csv_parser.py
scatterminal/data_layer_model.py
scatterminal/plot.py
scatterminal/py.typed
scatterminal/terminal_layer_model.py
scatterminal-0.1.2.dist-info/METADATA
scatterminal-0.1.2.dist-info/WHEEL
scatterminal-0.1.2.dist-info/entry_points.txt
scatterminal-0.1.2.dist-info/licenses/LICENSE
scatterminal-0.1.2.dist-info/RECORD
