Metadata-Version: 2.4
Name: scatterminal
Version: 0.1.2
Summary: Draw scatter plot on terminal
Project-URL: Repository, https://github.com/atsuhiron/scatterminal.git
Author-email: atsuhiron <atsuronreplaced@gmail.com>
License-File: LICENSE
Classifier: Development Status :: 4 - Beta
Classifier: Intended Audience :: Science/Research
Classifier: Topic :: Scientific/Engineering :: Visualization
Classifier: Topic :: Terminals
Requires-Python: >=3.10.0
